scarabs/__init__.py
scarabs/task_factory.py
scarabs/nova/__init__.py
scarabs/nova/component/__init__.py
scarabs/nova/component/args_factory.py
scarabs/nova/component/collator_factory.py
scarabs/nova/component/data_factory.py
scarabs/nova/component/model_factory.py
scarabs/nova/component/template_factory.py
scarabs/nova/component/tokenizer_factory.py
scarabs/nova/component/train_factory.py
scarabs/nova/lion/__init__.py
scarabs/nova/lion/foreach.py
scarabs/nova/lion/lion_pytorch.py
scarabs/nova/lion/triton.py
scarabs/nova/metrics/__init__.py
scarabs/nova/metrics/accuracy/__init__.py
scarabs/nova/metrics/accuracy/accuracy.py
scarabs/nova/metrics/accuracy/app.py
scarabs/nova/metrics/bertscore/__init__.py
scarabs/nova/metrics/bertscore/app.py
scarabs/nova/metrics/bertscore/bertscore.py
scarabs/nova/metrics/bleu/__init__.py
scarabs/nova/metrics/bleu/app.py
scarabs/nova/metrics/bleu/bleu.py
scarabs/nova/metrics/bleu/tokenizer_13a.py
scarabs/nova/metrics/bleurt/__init__.py
scarabs/nova/metrics/bleurt/app.py
scarabs/nova/metrics/bleurt/bleurt.py
scarabs/nova/metrics/brier_score/__init__.py
scarabs/nova/metrics/brier_score/app.py
scarabs/nova/metrics/brier_score/brier_score.py
scarabs/nova/metrics/cer/__init__.py
scarabs/nova/metrics/cer/app.py
scarabs/nova/metrics/cer/cer.py
scarabs/nova/metrics/cer/test_cer.py
scarabs/nova/metrics/character/__init__.py
scarabs/nova/metrics/character/app.py
scarabs/nova/metrics/character/character.py
scarabs/nova/metrics/charcut_mt/__init__.py
scarabs/nova/metrics/charcut_mt/app.py
scarabs/nova/metrics/charcut_mt/charcut_mt.py
scarabs/nova/metrics/chrf/__init__.py
scarabs/nova/metrics/chrf/app.py
scarabs/nova/metrics/chrf/chrf.py
scarabs/nova/metrics/code_eval/__init__.py
scarabs/nova/metrics/code_eval/app.py
scarabs/nova/metrics/code_eval/code_eval.py
scarabs/nova/metrics/code_eval/execute.py
scarabs/nova/metrics/comet/__init__.py
scarabs/nova/metrics/comet/app.py
scarabs/nova/metrics/comet/comet.py
scarabs-0.1.2.dist-info/LICENSE
scarabs-0.1.2.dist-info/METADATA
scarabs-0.1.2.dist-info/WHEEL
scarabs-0.1.2.dist-info/top_level.txt
scarabs-0.1.2.dist-info/RECORD
